datahandling/__init__.py
datahandling/change_directory.py
datahandling/change_encoding.py
datahandling/convert_files.py
datahandling/create_text_for_all_files_in_pdf_dir.py
datahandling/del_jpg.py
datahandling/dict_to_json.py
datahandling/file_type.py
datahandling/json_to_dict.py
datahandling/pdf_to_txt.py
datahandling/read_txt.py
datahandling/string_to_text.py
debugging/__init__.py
debugging/find_function.py
debugging/import_module_from_path.py
errorhandling/__init__.py
errorhandling/custom_errors.py
exploration/__init__.py
exploration/count_nans.py
exploration/desciptive_statistics.py
exploration/mydf_statistics.py
exploration/nan_heatmap.py
lukasdata/__init__.py
lukasdata/analyze_datasets.py
lukasdata/change_directory.py
lukasdata/check_for_all_zeroes.py
lukasdata/concat_dfs.py
lukasdata/count_nans.py
lukasdata/create_mask.py
lukasdata/del_jpg.py
lukasdata/determine_file_type.py
lukasdata/dict_to_json.py
lukasdata/drop_column_with_na.py
lukasdata/drop_columns_permutation_score.py
lukasdata/get_list_intersection.py
lukasdata/get_number_columns.py
lukasdata/json_to_dict.py
lukasdata/keras_input.py
lukasdata/list_to_string.py
lukasdata/mean_impute.py
lukasdata/ml_model.py
lukasdata/na_counts.py
lukasdata/order_dict.py
lukasdata/permutation_importance.py
lukasdata/plot_metric_history.py
lukasdata/string_to_text.py
machine_learning/__init__.py
machine_learning/drop_columns_permutation_score.py
machine_learning/imputation_validation.py
machine_learning/keras_input.py
machine_learning/mean_impute.py
machine_learning/missing_forest.py
machine_learning/missing_forest_cross_validation.py
machine_learning/ml_model.py
machine_learning/my_logs.py
machine_learning/n_neighbor_optimization.py
machine_learning/permutation_importance.py
processing/__init__.py
processing/create_mask.py
processing/format_dates.py
processing/format_numbers.py
processing/format_string.py
processing/my_df.py
processing/my_list.py
processing/my_string.py
processing/order_dict.py
lukasdata-1.5.4.dist-info/METADATA
lukasdata-1.5.4.dist-info/WHEEL
lukasdata-1.5.4.dist-info/top_level.txt
lukasdata-1.5.4.dist-info/RECORD
